hides/__init__.py
hides/__main__.py
hides/hides.py
hides-0.0.2.dist-info/LICENSE
hides-0.0.2.dist-info/METADATA
hides-0.0.2.dist-info/WHEEL
hides-0.0.2.dist-info/entry_points.txt
hides-0.0.2.dist-info/top_level.txt
hides-0.0.2.dist-info/RECORD
